{
    "CurrentRole": [
        "艾莲"
    ],
    "LastUpdatedDate": "2024-07-08",
    "OtherRoles": [
        {
            "name": "艾莲",
            "Record": [
                {
                    "StartTime": "2024-07-04",
                    "EndTime": "2024-07-24",
                    "Version": 1.0,
                    "UpOrDown": "上"
                }
            ]
        },
        {
            "name":"朱鸢",
            "Record":[
                {
                    "StartTime":"2024-07-24",
                    "EndTime":"",
                    "Version":1.0,
                    "UpOrDown":"下"
                }
            ]
        }
    ]
}